{
  "date" : "Fri, 19 Jun, 2026 17:16:10 +0000",
  "doco" : "For each file: start is seconds after start activity occurred. Length = milliseconds activity took",
  "files" : [{
    "name" : "/fsh-generated/resources/ImplementationGuide-ans.fhir.fr.pdsm4dmp.json",
    "size" : 23377,
    "processes" : [{
      "activity" : "load",
      "start" : 117,
      "length" : 253
    },
    {
      "activity" : "checkR4R4B",
      "start" : 118,
      "length" : 17
    },
    {
      "activity" : "generateNarratives",
      "start" : 118,
      "length" : 89
    },
    {
      "activity" : "validate",
      "start" : 126,
      "length" : 6895
    },
    {
      "activity" : "scanForUsageStats",
      "start" : 133,
      "length" : 1
    },
    {
      "activity" : "translate",
      "start" : 142,
      "length" : 23
    },
    {
      "activity" : "generate1",
      "start" : 142,
      "length" : 195
    },
    {
      "activity" : "generate2",
      "start" : 150,
      "length" : 495
    },
    {
      "activity" : "generateValidationPack",
      "start" : 185,
      "length" : 7
    },
    {
      "activity" : "scanExamplesForR5",
      "start" : 215,
      "length" : 1
    }]
  },
  {
    "name" : "fsh-generated/resources/Binary-AuthorDispositif.json",
    "size" : 1341,
    "processes" : [{
      "activity" : "loadResources",
      "start" : 116,
      "length" : 3
    },
    {
      "activity" : "load-configure",
      "start" : 118,
      "length" : 2
    },
    {
      "activity" : "generateNarratives",
      "start" : 118,
      "length" : 1
    },
    {
      "activity" : "validate",
      "start" : 133,
      "length" : 1
    },
    {
      "activity" : "translate",
      "start" : 142,
      "length" : 9
    },
    {
      "activity" : "generate1",
      "start" : 142,
      "length" : 8
    },
    {
      "activity" : "generate2",
      "start" : 150,
      "length" : 15
    }]
  },
  {
    "name" : "fsh-generated/resources/Binary-AuthorInstitutionCabinetRPPS.json",
    "size" : 1351,
    "processes" : [{
      "activity" : "loadResources",
      "start" : 116,
      "length" : 2
    },
    {
      "activity" : "validate",
      "start" : 133,
      "length" : 1
    },
    {
      "activity" : "translate",
      "start" : 142,
      "length" : 7
    },
    {
      "activity" : "generate1",
      "start" : 142,
      "length" : 7
    },
    {
      "activity" : "generate2",
      "start" : 150,
      "length" : 13
    }]
  },
  {
    "name" : "fsh-generated/resources/Binary-AuthorInstitutionSNR.json",
    "size" : 1343,
    "processes" : [{
      "activity" : "loadResources",
      "start" : 116,
      "length" : 2
    },
    {
      "activity" : "validate",
      "start" : 133,
      "length" : 1
    },
    {
      "activity" : "translate",
      "start" : 142,
      "length" : 7
    },
    {
      "activity" : "generate1",
      "start" : 142,
      "length" : 8
    },
    {
      "activity" : "generate2",
      "start" : 150,
      "length" : 13
    }]
  },
  {
    "name" : "fsh-generated/resources/Binary-AuthorInstitutionStructure.json",
    "size" : 1349,
    "processes" : [{
      "activity" : "loadResources",
      "start" : 116,
      "length" : 1
    },
    {
      "activity" : "generateNarratives",
      "start" : 118,
      "length" : 1
    },
    {
      "activity" : "translate",
      "start" : 142,
      "length" : 7
    },
    {
      "activity" : "generate1",
      "start" : 142,
      "length" : 6
    },
    {
      "activity" : "generate2",
      "start" : 150,
      "length" : 12
    }]
  },
  {
    "name" : "fsh-generated/resources/Binary-AuthorPSCabinetRPPS.json",
    "size" : 1344,
    "processes" : [{
      "activity" : "loadResources",
      "start" : 116,
      "length" : 1
    },
    {
      "activity" : "validate",
      "start" : 133,
      "length" : 1
    },
    {
      "activity" : "translate",
      "start" : 142,
      "length" : 7
    },
    {
      "activity" : "generate1",
      "start" : 142,
      "length" : 10
    },
    {
      "activity" : "generate2",
      "start" : 150,
      "length" : 12
    }]
  },
  {
    "name" : "fsh-generated/resources/Binary-AuthorPatient.json",
    "size" : 1338,
    "processes" : [{
      "activity" : "loadResources",
      "start" : 116,
      "length" : 2
    },
    {
      "activity" : "validate",
      "start" : 133,
      "length" : 1
    },
    {
      "activity" : "translate",
      "start" : 142,
      "length" : 7
    },
    {
      "activity" : "generate1",
      "start" : 142,
      "length" : 8
    },
    {
      "activity" : "generate2",
      "start" : 150,
      "length" : 14
    }]
  },
  {
    "name" : "fsh-generated/resources/Binary-AuthorStructure.json",
    "size" : 1340,
    "processes" : [{
      "activity" : "loadResources",
      "start" : 116,
      "length" : 1
    },
    {
      "activity" : "validate",
      "start" : 133,
      "length" : 1
    },
    {
      "activity" : "translate",
      "start" : 142,
      "length" : 6
    },
    {
      "activity" : "generate1",
      "start" : 142,
      "length" : 6
    },
    {
      "activity" : "generate2",
      "start" : 150,
      "length" : 13
    }]
  },
  {
    "name" : "fsh-generated/resources/ConceptMap-documentReferenceToPDSM.json",
    "size" : 7426,
    "processes" : [{
      "activity" : "loadResources",
      "start" : 116,
      "length" : 3
    },
    {
      "activity" : "load",
      "start" : 116,
      "length" : 16
    },
    {
      "activity" : "load",
      "start" : 117,
      "length" : 6
    },
    {
      "activity" : "checkR4R4B",
      "start" : 118,
      "length" : 2
    },
    {
      "activity" : "generateNarratives",
      "start" : 118,
      "length" : 36
    },
    {
      "activity" : "validate",
      "start" : 123,
      "length" : 899
    },
    {
      "activity" : "validate",
      "start" : 126,
      "length" : 1
    },
    {
      "activity" : "checkConformanceResources3",
      "start" : 133,
      "length" : 1
    },
    {
      "activity" : "translate",
      "start" : 142,
      "length" : 6
    },
    {
      "activity" : "generate1",
      "start" : 142,
      "length" : 61
    },
    {
      "activity" : "generate2",
      "start" : 150,
      "length" : 214
    },
    {
      "activity" : "generateValidationPack",
      "start" : 185,
      "length" : 2
    }]
  },
  {
    "name" : "fsh-generated/resources/ConceptMap-submissionSetToPDSM.json",
    "size" : 3412,
    "processes" : [{
      "activity" : "loadResources",
      "start" : 116,
      "length" : 3
    },
    {
      "activity" : "load",
      "start" : 116,
      "length" : 7
    },
    {
      "activity" : "load",
      "start" : 117,
      "length" : 5
    },
    {
      "activity" : "generateNarratives",
      "start" : 118,
      "length" : 777
    },
    {
      "activity" : "validate",
      "start" : 124,
      "length" : 58
    },
    {
      "activity" : "validate",
      "start" : 133,
      "length" : 1
    },
    {
      "activity" : "translate",
      "start" : 142,
      "length" : 5
    },
    {
      "activity" : "generate1",
      "start" : 143,
      "length" : 31
    },
    {
      "activity" : "generate2",
      "start" : 151,
      "length" : 97
    },
    {
      "activity" : "generateValidationPack",
      "start" : 185,
      "length" : 1
    }]
  },
  {
    "name" : "fsh-generated/resources/DocumentReference-example-td3-1a-cr-consultation.json",
    "size" : 3088,
    "processes" : [{
      "activity" : "loadResources",
      "start" : 116,
      "length" : 3
    },
    {
      "activity" : "checkR4R4B",
      "start" : 118,
      "length" : 1
    },
    {
      "activity" : "generateNarratives",
      "start" : 119,
      "length" : 2689
    },
    {
      "activity" : "validate",
      "start" : 133,
      "length" : 4470
    },
    {
      "activity" : "translate",
      "start" : 142,
      "length" : 11
    },
    {
      "activity" : "generate1",
      "start" : 143,
      "length" : 31
    },
    {
      "activity" : "generate2",
      "start" : 151,
      "length" : 50
    }]
  },
  {
    "name" : "fsh-generated/resources/DocumentReference-example-td3-1a-fhir-document.json",
    "size" : 3049,
    "processes" : [{
      "activity" : "loadResources",
      "start" : 116,
      "length" : 3
    },
    {
      "activity" : "checkR4R4B",
      "start" : 118,
      "length" : 1
    },
    {
      "activity" : "generateNarratives",
      "start" : 122,
      "length" : 514
    },
    {
      "activity" : "scanForUsageStats",
      "start" : 133,
      "length" : 1
    },
    {
      "activity" : "validate",
      "start" : 138,
      "length" : 831
    },
    {
      "activity" : "translate",
      "start" : 142,
      "length" : 3
    },
    {
      "activity" : "generate1",
      "start" : 143,
      "length" : 26
    },
    {
      "activity" : "generate2",
      "start" : 151,
      "length" : 44
    }]
  },
  {
    "name" : "fsh-generated/resources/DocumentReference-example-td3-1a-ordonnance.json",
    "size" : 3017,
    "processes" : [{
      "activity" : "loadResources",
      "start" : 116,
      "length" : 3
    },
    {
      "activity" : "load",
      "start" : 116,
      "length" : 1
    },
    {
      "activity" : "load-configure",
      "start" : 118,
      "length" : 1
    },
    {
      "activity" : "checkR4R4B",
      "start" : 118,
      "length" : 1
    },
    {
      "activity" : "generateNarratives",
      "start" : 122,
      "length" : 24
    },
    {
      "activity" : "validate",
      "start" : 139,
      "length" : 356
    },
    {
      "activity" : "translate",
      "start" : 142,
      "length" : 4
    },
    {
      "activity" : "generate1",
      "start" : 143,
      "length" : 24
    },
    {
      "activity" : "generate2",
      "start" : 151,
      "length" : 45
    }]
  },
  {
    "name" : "fsh-generated/resources/StructureDefinition-ActorPS.json",
    "size" : 2260,
    "processes" : [{
      "activity" : "loadResources",
      "start" : 116,
      "length" : 3
    },
    {
      "activity" : "load",
      "start" : 116,
      "length" : 7
    },
    {
      "activity" : "generateSnapshots",
      "start" : 117,
      "length" : 28
    },
    {
      "activity" : "generateNarratives",
      "start" : 122,
      "length" : 79
    },
    {
      "activity" : "validate",
      "start" : 124,
      "length" : 242
    },
    {
      "activity" : "checkConformanceResources",
      "start" : 133,
      "length" : 1
    },
    {
      "activity" : "validate",
      "start" : 139,
      "length" : 1
    },
    {
      "activity" : "translate",
      "start" : 142,
      "length" : 1
    },
    {
      "activity" : "generate1",
      "start" : 143,
      "length" : 92
    },
    {
      "activity" : "generate2",
      "start" : 151,
      "length" : 948
    },
    {
      "activity" : "generate2",
      "start" : 158,
      "length" : 241
    },
    {
      "activity" : "makeDependencies",
      "start" : 162,
      "length" : 1
    },
    {
      "activity" : "generateValidationPack",
      "start" : 185,
      "length" : 2
    }]
  },
  {
    "name" : "fsh-generated/resources/StructureDefinition-ActorPatient.json",
    "size" : 2164,
    "processes" : [{
      "activity" : "loadResources",
      "start" : 116,
      "length" : 2
    },
    {
      "activity" : "load",
      "start" : 116,
      "length" : 4
    },
    {
      "activity" : "generateSnapshots",
      "start" : 117,
      "length" : 11
    },
    {
      "activity" : "generateNarratives",
      "start" : 122,
      "length" : 21
    },
    {
      "activity" : "validate",
      "start" : 124,
      "length" : 193
    },
    {
      "activity" : "checkConformanceResources",
      "start" : 133,
      "length" : 1
    },
    {
      "activity" : "translate",
      "start" : 142,
      "length" : 1
    },
    {
      "activity" : "generate1",
      "start" : 143,
      "length" : 83
    },
    {
      "activity" : "generate2",
      "start" : 152,
      "length" : 395
    },
    {
      "activity" : "generate2",
      "start" : 158,
      "length" : 113
    },
    {
      "activity" : "generateValidationPack",
      "start" : 186,
      "length" : 2
    }]
  },
  {
    "name" : "fsh-generated/resources/StructureDefinition-ActorSNR.json",
    "size" : 2209,
    "processes" : [{
      "activity" : "loadResources",
      "start" : 116,
      "length" : 3
    },
    {
      "activity" : "load",
      "start" : 116,
      "length" : 5
    },
    {
      "activity" : "generateSnapshots",
      "start" : 117,
      "length" : 11
    },
    {
      "activity" : "loadDepInfo",
      "start" : 118,
      "length" : 1
    },
    {
      "activity" : "generateNarratives",
      "start" : 122,
      "length" : 21
    },
    {
      "activity" : "validate",
      "start" : 125,
      "length" : 123
    },
    {
      "activity" : "validate",
      "start" : 139,
      "length" : 1
    },
    {
      "activity" : "translate",
      "start" : 142,
      "length" : 1
    },
    {
      "activity" : "generate1",
      "start" : 143,
      "length" : 77
    },
    {
      "activity" : "generate2",
      "start" : 152,
      "length" : 313
    },
    {
      "activity" : "generate2",
      "start" : 158,
      "length" : 89
    },
    {
      "activity" : "generateValidationPack",
      "start" : 186,
      "length" : 2
    }]
  },
  {
    "name" : "fsh-generated/resources/StructureDefinition-ActorSystem.json",
    "size" : 2127,
    "processes" : [{
      "activity" : "loadResources",
      "start" : 116,
      "length" : 3
    },
    {
      "activity" : "load",
      "start" : 116,
      "length" : 5
    },
    {
      "activity" : "generateSnapshots",
      "start" : 117,
      "length" : 13
    },
    {
      "activity" : "generateNarratives",
      "start" : 122,
      "length" : 20
    },
    {
      "activity" : "validate",
      "start" : 125,
      "length" : 111
    },
    {
      "activity" : "checkConformanceResources3",
      "start" : 133,
      "length" : 1
    },
    {
      "activity" : "scanForUsageStats",
      "start" : 133,
      "length" : 1
    },
    {
      "activity" : "generate1",
      "start" : 143,
      "length" : 80
    },
    {
      "activity" : "generate2",
      "start" : 152,
      "length" : 294
    },
    {
      "activity" : "generate2",
      "start" : 158,
      "length" : 65
    },
    {
      "activity" : "generateValidationPack",
      "start" : 186,
      "length" : 2
    }]
  },
  {
    "name" : "fsh-generated/resources/StructureDefinition-ActorXDS.json",
    "size" : 5924,
    "processes" : [{
      "activity" : "loadResources",
      "start" : 116,
      "length" : 3
    },
    {
      "activity" : "load",
      "start" : 116,
      "length" : 7
    },
    {
      "activity" : "generateSnapshots",
      "start" : 117,
      "length" : 1
    },
    {
      "activity" : "generateNarratives",
      "start" : 122,
      "length" : 22
    },
    {
      "activity" : "validate",
      "start" : 125,
      "length" : 115
    },
    {
      "activity" : "checkConformanceResources",
      "start" : 133,
      "length" : 1
    },
    {
      "activity" : "validate",
      "start" : 139,
      "length" : 1
    },
    {
      "activity" : "translate",
      "start" : 142,
      "length" : 2
    },
    {
      "activity" : "generate1",
      "start" : 143,
      "length" : 84
    },
    {
      "activity" : "generate2",
      "start" : 153,
      "length" : 285
    },
    {
      "activity" : "generate2",
      "start" : 158,
      "length" : 61
    },
    {
      "activity" : "generateValidationPack",
      "start" : 186,
      "length" : 2
    }]
  },
  {
    "name" : "fsh-generated/resources/StructureDefinition-Author.json",
    "size" : 4643,
    "processes" : [{
      "activity" : "loadResources",
      "start" : 116,
      "length" : 3
    },
    {
      "activity" : "load",
      "start" : 116,
      "length" : 6
    },
    {
      "activity" : "generateSnapshots",
      "start" : 117,
      "length" : 16
    },
    {
      "activity" : "generateNarratives",
      "start" : 122,
      "length" : 24
    },
    {
      "activity" : "validate",
      "start" : 125,
      "length" : 65
    },
    {
      "activity" : "translate",
      "start" : 142,
      "length" : 1
    },
    {
      "activity" : "generate1",
      "start" : 143,
      "length" : 75
    },
    {
      "activity" : "generate2",
      "start" : 153,
      "length" : 290
    },
    {
      "activity" : "generate2",
      "start" : 158,
      "length" : 50
    },
    {
      "activity" : "generateValidationPack",
      "start" : 186,
      "length" : 2
    }]
  },
  {
    "name" : "fsh-generated/resources/StructureDefinition-AuthorDocumentEntry.json",
    "size" : 4337,
    "processes" : [{
      "activity" : "loadResources",
      "start" : 116,
      "length" : 3
    },
    {
      "activity" : "load",
      "start" : 116,
      "length" : 5
    },
    {
      "activity" : "generateSnapshots",
      "start" : 117,
      "length" : 11
    },
    {
      "activity" : "generateNarratives",
      "start" : 122,
      "length" : 16
    },
    {
      "activity" : "validate",
      "start" : 125,
      "length" : 94
    },
    {
      "activity" : "checkConformanceResources",
      "start" : 133,
      "length" : 1
    },
    {
      "activity" : "validate",
      "start" : 139,
      "length" : 1
    },
    {
      "activity" : "translate",
      "start" : 142,
      "length" : 1
    },
    {
      "activity" : "generate1",
      "start" : 143,
      "length" : 67
    },
    {
      "activity" : "generate2",
      "start" : 153,
      "length" : 246
    },
    {
      "activity" : "generate2",
      "start" : 158,
      "length" : 56
    },
    {
      "activity" : "generateValidationPack",
      "start" : 186,
      "length" : 2
    },
    {
      "activity" : "scanExamplesForR5",
      "start" : 215,
      "length" : 1
    }]
  },
  {
    "name" : "fsh-generated/resources/StructureDefinition-AuthorInstitution.json",
    "size" : 7143,
    "processes" : [{
      "activity" : "loadResources",
      "start" : 116,
      "length" : 3
    },
    {
      "activity" : "load",
      "start" : 116,
      "length" : 7
    },
    {
      "activity" : "generateSnapshots",
      "start" : 117,
      "length" : 9
    },
    {
      "activity" : "generateNarratives",
      "start" : 122,
      "length" : 19
    },
    {
      "activity" : "validate",
      "start" : 125,
      "length" : 116
    },
    {
      "activity" : "validate",
      "start" : 139,
      "length" : 1
    },
    {
      "activity" : "translate",
      "start" : 142,
      "length" : 1
    },
    {
      "activity" : "generate1",
      "start" : 143,
      "length" : 83
    },
    {
      "activity" : "generate2",
      "start" : 154,
      "length" : 263
    },
    {
      "activity" : "generate2",
      "start" : 158,
      "length" : 61
    },
    {
      "activity" : "generateValidationPack",
      "start" : 186,
      "length" : 2
    }]
  },
  {
    "name" : "fsh-generated/resources/StructureDefinition-AuthorSubmissionSet.json",
    "size" : 2401,
    "processes" : [{
      "activity" : "loadResources",
      "start" : 116,
      "length" : 3
    },
    {
      "activity" : "load",
      "start" : 116,
      "length" : 4
    },
    {
      "activity" : "generateSnapshots",
      "start" : 117,
      "length" : 9
    },
    {
      "activity" : "generateNarratives",
      "start" : 122,
      "length" : 14
    },
    {
      "activity" : "validate",
      "start" : 125,
      "length" : 45
    },
    {
      "activity" : "checkConformanceResources",
      "start" : 133,
      "length" : 1
    },
    {
      "activity" : "checkConformanceResources3",
      "start" : 133,
      "length" : 1
    },
    {
      "activity" : "translate",
      "start" : 142,
      "length" : 1
    },
    {
      "activity" : "generate1",
      "start" : 143,
      "length" : 53
    },
    {
      "activity" : "generate2",
      "start" : 154,
      "length" : 220
    },
    {
      "activity" : "generate2",
      "start" : 158,
      "length" : 42
    },
    {
      "activity" : "generateValidationPack",
      "start" : 186,
      "length" : 1
    }]
  },
  {
    "name" : "fsh-generated/resources/StructureDefinition-DocumentEntry.json",
    "size" : 21414,
    "processes" : [{
      "activity" : "loadResources",
      "start" : 116,
      "length" : 7
    },
    {
      "activity" : "load",
      "start" : 116,
      "length" : 11
    },
    {
      "activity" : "generateSnapshots",
      "start" : 117,
      "length" : 33
    },
    {
      "activity" : "generateNarratives",
      "start" : 122,
      "length" : 54
    },
    {
      "activity" : "validate",
      "start" : 125,
      "length" : 376
    },
    {
      "activity" : "validate",
      "start" : 139,
      "length" : 1
    },
    {
      "activity" : "translate",
      "start" : 142,
      "length" : 4
    },
    {
      "activity" : "generate1",
      "start" : 143,
      "length" : 266
    },
    {
      "activity" : "generate2",
      "start" : 154,
      "length" : 695
    },
    {
      "activity" : "generate2",
      "start" : 158,
      "length" : 142
    },
    {
      "activity" : "generateValidationPack",
      "start" : 186,
      "length" : 7
    }]
  },
  {
    "name" : "fsh-generated/resources/StructureDefinition-EventCode.json",
    "size" : 1766,
    "processes" : [{
      "activity" : "loadResources",
      "start" : 116,
      "length" : 2
    },
    {
      "activity" : "load",
      "start" : 117,
      "length" : 5
    },
    {
      "activity" : "generateSnapshots",
      "start" : 117,
      "length" : 8
    },
    {
      "activity" : "loadInfo",
      "start" : 118,
      "length" : 1
    },
    {
      "activity" : "generateNarratives",
      "start" : 122,
      "length" : 11
    },
    {
      "activity" : "validate",
      "start" : 126,
      "length" : 26
    },
    {
      "activity" : "generate1",
      "start" : 144,
      "length" : 37
    },
    {
      "activity" : "generate2",
      "start" : 155,
      "length" : 224
    },
    {
      "activity" : "generate2",
      "start" : 159,
      "length" : 27
    },
    {
      "activity" : "generateValidationPack",
      "start" : 186,
      "length" : 1
    }]
  },
  {
    "name" : "fsh-generated/resources/StructureDefinition-Folder.json",
    "size" : 6382,
    "processes" : [{
      "activity" : "loadResources",
      "start" : 116,
      "length" : 3
    },
    {
      "activity" : "load",
      "start" : 117,
      "length" : 6
    },
    {
      "activity" : "generateSnapshots",
      "start" : 117,
      "length" : 10
    },
    {
      "activity" : "load-configure",
      "start" : 118,
      "length" : 1
    },
    {
      "activity" : "generateNarratives",
      "start" : 122,
      "length" : 20
    },
    {
      "activity" : "validate",
      "start" : 126,
      "length" : 101
    },
    {
      "activity" : "checkConformanceResources",
      "start" : 133,
      "length" : 1
    },
    {
      "activity" : "scanForUsageStats",
      "start" : 133,
      "length" : 1
    },
    {
      "activity" : "validate",
      "start" : 139,
      "length" : 1
    },
    {
      "activity" : "translate",
      "start" : 142,
      "length" : 1
    },
    {
      "activity" : "generate1",
      "start" : 144,
      "length" : 94
    },
    {
      "activity" : "generate2",
      "start" : 155,
      "length" : 309
    },
    {
      "activity" : "generate2",
      "start" : 159,
      "length" : 57
    },
    {
      "activity" : "generateValidationPack",
      "start" : 186,
      "length" : 3
    }]
  },
  {
    "name" : "fsh-generated/resources/StructureDefinition-Identifiant.json",
    "size" : 1638,
    "processes" : [{
      "activity" : "loadResources",
      "start" : 116,
      "length" : 2
    },
    {
      "activity" : "load",
      "start" : 117,
      "length" : 3
    },
    {
      "activity" : "generateSnapshots",
      "start" : 117,
      "length" : 5
    },
    {
      "activity" : "generateNarratives",
      "start" : 122,
      "length" : 16
    },
    {
      "activity" : "validate",
      "start" : 126,
      "length" : 33
    },
    {
      "activity" : "checkConformanceResources3",
      "start" : 133,
      "length" : 1
    },
    {
      "activity" : "translate",
      "start" : 142,
      "length" : 1
    },
    {
      "activity" : "generate1",
      "start" : 144,
      "length" : 52
    },
    {
      "activity" : "generate2",
      "start" : 155,
      "length" : 269
    },
    {
      "activity" : "generate2",
      "start" : 159,
      "length" : 34
    },
    {
      "activity" : "generateValidationPack",
      "start" : 186,
      "length" : 1
    },
    {
      "activity" : "scanProfilesForR5",
      "start" : 215,
      "length" : 1
    }]
  },
  {
    "name" : "fsh-generated/resources/StructureDefinition-IdentifiantSysteme.json",
    "size" : 1054,
    "processes" : [{
      "activity" : "loadResources",
      "start" : 116,
      "length" : 2
    },
    {
      "activity" : "load",
      "start" : 117,
      "length" : 3
    },
    {
      "activity" : "generateSnapshots",
      "start" : 117,
      "length" : 5
    },
    {
      "activity" : "generateNarratives",
      "start" : 122,
      "length" : 10
    },
    {
      "activity" : "validate",
      "start" : 126,
      "length" : 55
    },
    {
      "activity" : "validate",
      "start" : 139,
      "length" : 1
    },
    {
      "activity" : "generate1",
      "start" : 144,
      "length" : 41
    },
    {
      "activity" : "generate2",
      "start" : 156,
      "length" : 250
    },
    {
      "activity" : "generate2",
      "start" : 159,
      "length" : 40
    },
    {
      "activity" : "generateValidationPack",
      "start" : 186,
      "length" : 1
    }]
  },
  {
    "name" : "fsh-generated/resources/StructureDefinition-MatriculeINS.json",
    "size" : 1397,
    "processes" : [{
      "activity" : "loadResources",
      "start" : 116,
      "length" : 2
    },
    {
      "activity" : "load",
      "start" : 117,
      "length" : 3
    },
    {
      "activity" : "generateSnapshots",
      "start" : 117,
      "length" : 4
    },
    {
      "activity" : "generateNarratives",
      "start" : 122,
      "length" : 7
    },
    {
      "activity" : "validate",
      "start" : 126,
      "length" : 41
    },
    {
      "activity" : "translate",
      "start" : 142,
      "length" : 1
    },
    {
      "activity" : "generate1",
      "start" : 144,
      "length" : 34
    },
    {
      "activity" : "generate2",
      "start" : 156,
      "length" : 212
    },
    {
      "activity" : "generate2",
      "start" : 159,
      "length" : 37
    },
    {
      "activity" : "generateValidationPack",
      "start" : 186,
      "length" : 1
    }]
  },
  {
    "name" : "fsh-generated/resources/StructureDefinition-PSIdNat.json",
    "size" : 2251,
    "processes" : [{
      "activity" : "loadResources",
      "start" : 116,
      "length" : 2
    },
    {
      "activity" : "load",
      "start" : 117,
      "length" : 3
    },
    {
      "activity" : "generateSnapshots",
      "start" : 117,
      "length" : 5
    },
    {
      "activity" : "generateNarratives",
      "start" : 122,
      "length" : 9
    },
    {
      "activity" : "validate",
      "start" : 126,
      "length" : 50
    },
    {
      "activity" : "checkConformanceResources",
      "start" : 133,
      "length" : 1
    },
    {
      "activity" : "validate",
      "start" : 139,
      "length" : 1
    },
    {
      "activity" : "translate",
      "start" : 142,
      "length" : 1
    },
    {
      "activity" : "generate1",
      "start" : 144,
      "length" : 38
    },
    {
      "activity" : "generate2",
      "start" : 156,
      "length" : 227
    },
    {
      "activity" : "generate2",
      "start" : 159,
      "length" : 35
    },
    {
      "activity" : "generateValidationPack",
      "start" : 186,
      "length" : 1
    },
    {
      "activity" : "scanExamplesForR5",
      "start" : 215,
      "length" : 1
    }]
  },
  {
    "name" : "fsh-generated/resources/StructureDefinition-PatientId.json",
    "size" : 2528,
    "processes" : [{
      "activity" : "loadResources",
      "start" : 116,
      "length" : 2
    },
    {
      "activity" : "load",
      "start" : 117,
      "length" : 4
    },
    {
      "activity" : "generateSnapshots",
      "start" : 117,
      "length" : 7
    },
    {
      "activity" : "generateNarratives",
      "start" : 122,
      "length" : 9
    },
    {
      "activity" : "validate",
      "start" : 126,
      "length" : 62
    },
    {
      "activity" : "validate",
      "start" : 133,
      "length" : 1
    },
    {
      "activity" : "generate1",
      "start" : 144,
      "length" : 69
    },
    {
      "activity" : "generate2",
      "start" : 156,
      "length" : 206
    },
    {
      "activity" : "generate2",
      "start" : 159,
      "length" : 42
    },
    {
      "activity" : "generateValidationPack",
      "start" : 186,
      "length" : 1
    }]
  },
  {
    "name" : "fsh-generated/resources/StructureDefinition-SNR.json",
    "size" : 1055,
    "processes" : [{
      "activity" : "loadResources",
      "start" : 116,
      "length" : 1
    },
    {
      "activity" : "load",
      "start" : 117,
      "length" : 3
    },
    {
      "activity" : "generateSnapshots",
      "start" : 117,
      "length" : 3
    },
    {
      "activity" : "generateNarratives",
      "start" : 122,
      "length" : 7
    },
    {
      "activity" : "validate",
      "start" : 126,
      "length" : 34
    },
    {
      "activity" : "checkConformanceResources3",
      "start" : 133,
      "length" : 1
    },
    {
      "activity" : "validate",
      "start" : 139,
      "length" : 1
    },
    {
      "activity" : "translate",
      "start" : 142,
      "length" : 1
    },
    {
      "activity" : "generate1",
      "start" : 144,
      "length" : 38
    },
    {
      "activity" : "generate2",
      "start" : 156,
      "length" : 181
    },
    {
      "activity" : "generate2",
      "start" : 159,
      "length" : 27
    },
    {
      "activity" : "generateValidationPack",
      "start" : 186,
      "length" : 1
    }]
  },
  {
    "name" : "fsh-generated/resources/StructureDefinition-SourcePatientId.json",
    "size" : 2661,
    "processes" : [{
      "activity" : "loadResources",
      "start" : 116,
      "length" : 2
    },
    {
      "activity" : "load",
      "start" : 117,
      "length" : 3
    },
    {
      "activity" : "generateSnapshots",
      "start" : 117,
      "length" : 8
    },
    {
      "activity" : "generateNarratives",
      "start" : 122,
      "length" : 10
    },
    {
      "activity" : "validate",
      "start" : 126,
      "length" : 38
    },
    {
      "activity" : "generate1",
      "start" : 144,
      "length" : 46
    },
    {
      "activity" : "generate2",
      "start" : 157,
      "length" : 193
    },
    {
      "activity" : "generate2",
      "start" : 159,
      "length" : 30
    },
    {
      "activity" : "generateValidationPack",
      "start" : 186,
      "length" : 1
    }]
  },
  {
    "name" : "fsh-generated/resources/StructureDefinition-SourcePatientInfo.json",
    "size" : 4955,
    "processes" : [{
      "activity" : "loadResources",
      "start" : 116,
      "length" : 2
    },
    {
      "activity" : "load",
      "start" : 117,
      "length" : 6
    },
    {
      "activity" : "generateSnapshots",
      "start" : 117,
      "length" : 8
    },
    {
      "activity" : "generateNarratives",
      "start" : 123,
      "length" : 16
    },
    {
      "activity" : "validate",
      "start" : 126,
      "length" : 85
    },
    {
      "activity" : "checkConformanceResources",
      "start" : 133,
      "length" : 1
    },
    {
      "activity" : "checkConformanceResources2",
      "start" : 133,
      "length" : 1
    },
    {
      "activity" : "validate",
      "start" : 139,
      "length" : 1
    },
    {
      "activity" : "translate",
      "start" : 142,
      "length" : 1
    },
    {
      "activity" : "generate1",
      "start" : 144,
      "length" : 84
    },
    {
      "activity" : "generate2",
      "start" : 157,
      "length" : 246
    },
    {
      "activity" : "generate2",
      "start" : 159,
      "length" : 51
    },
    {
      "activity" : "generateValidationPack",
      "start" : 186,
      "length" : 2
    }]
  },
  {
    "name" : "fsh-generated/resources/StructureDefinition-StructIdNat.json",
    "size" : 1629,
    "processes" : [{
      "activity" : "loadResources",
      "start" : 116,
      "length" : 2
    },
    {
      "activity" : "load",
      "start" : 117,
      "length" : 3
    },
    {
      "activity" : "generateSnapshots",
      "start" : 117,
      "length" : 7
    },
    {
      "activity" : "generateNarratives",
      "start" : 123,
      "length" : 8
    },
    {
      "activity" : "validate",
      "start" : 126,
      "length" : 23
    },
    {
      "activity" : "translate",
      "start" : 142,
      "length" : 1
    },
    {
      "activity" : "generate1",
      "start" : 144,
      "length" : 35
    },
    {
      "activity" : "generate2",
      "start" : 157,
      "length" : 166
    },
    {
      "activity" : "generate2",
      "start" : 159,
      "length" : 23
    },
    {
      "activity" : "generateValidationPack",
      "start" : 186,
      "length" : 1
    }]
  },
  {
    "name" : "fsh-generated/resources/StructureDefinition-SubmissionSet.json",
    "size" : 8029,
    "processes" : [{
      "activity" : "loadResources",
      "start" : 116,
      "length" : 3
    },
    {
      "activity" : "load",
      "start" : 117,
      "length" : 6
    },
    {
      "activity" : "generateSnapshots",
      "start" : 117,
      "length" : 13
    },
    {
      "activity" : "generateNarratives",
      "start" : 123,
      "length" : 19
    },
    {
      "activity" : "validate",
      "start" : 126,
      "length" : 119
    },
    {
      "activity" : "checkConformanceResources3",
      "start" : 133,
      "length" : 1
    },
    {
      "activity" : "validate",
      "start" : 139,
      "length" : 1
    },
    {
      "activity" : "translate",
      "start" : 142,
      "length" : 2
    },
    {
      "activity" : "generate1",
      "start" : 144,
      "length" : 111
    },
    {
      "activity" : "generate2",
      "start" : 157,
      "length" : 268
    },
    {
      "activity" : "generate2",
      "start" : 159,
      "length" : 53
    },
    {
      "activity" : "generateValidationPack",
      "start" : 186,
      "length" : 3
    }]
  },
  {
    "name" : "input/examples/Bundle-example-td2-1-remplacement.json",
    "size" : 7701,
    "processes" : [{
      "activity" : "loadResources",
      "start" : 116,
      "length" : 3
    },
    {
      "activity" : "load",
      "start" : 116,
      "length" : 22
    },
    {
      "activity" : "load",
      "start" : 117,
      "length" : 1
    },
    {
      "activity" : "checkR4R4B",
      "start" : 118,
      "length" : 2
    },
    {
      "activity" : "generateNarratives",
      "start" : 123,
      "length" : 381
    },
    {
      "activity" : "validate",
      "start" : 139,
      "length" : 2334
    },
    {
      "activity" : "translate",
      "start" : 142,
      "length" : 6
    },
    {
      "activity" : "generate1",
      "start" : 144,
      "length" : 27
    },
    {
      "activity" : "generate2",
      "start" : 157,
      "length" : 76
    }]
  },
  {
    "name" : "input/examples/Bundle-example-td2-iti65-lot-soumission.json",
    "size" : 6970,
    "processes" : [{
      "activity" : "loadResources",
      "start" : 116,
      "length" : 4
    },
    {
      "activity" : "load",
      "start" : 116,
      "length" : 2
    },
    {
      "activity" : "load",
      "start" : 117,
      "length" : 1
    },
    {
      "activity" : "checkR4R4B",
      "start" : 118,
      "length" : 2
    },
    {
      "activity" : "generateNarratives",
      "start" : 123,
      "length" : 13
    },
    {
      "activity" : "validate",
      "start" : 141,
      "length" : 543
    },
    {
      "activity" : "translate",
      "start" : 142,
      "length" : 6
    },
    {
      "activity" : "generate1",
      "start" : 144,
      "length" : 21
    },
    {
      "activity" : "generate2",
      "start" : 158,
      "length" : 63
    }]
  },
  {
    "name" : "input/examples/DocumentReference-doc-x-id.json",
    "size" : 2801,
    "processes" : [{
      "activity" : "loadResources",
      "start" : 116,
      "length" : 2
    },
    {
      "activity" : "checkR4R4B",
      "start" : 118,
      "length" : 1
    },
    {
      "activity" : "generateNarratives",
      "start" : 123,
      "length" : 267
    },
    {
      "activity" : "validate",
      "start" : 142,
      "length" : 29
    },
    {
      "activity" : "translate",
      "start" : 142,
      "length" : 5
    },
    {
      "activity" : "generate1",
      "start" : 144,
      "length" : 22
    },
    {
      "activity" : "generate2",
      "start" : 158,
      "length" : 31
    },
    {
      "activity" : "generateExampleZip",
      "start" : 185,
      "length" : 1
    }]
  },
  {
    "name" : "input/examples/DocumentReference-example-td2-iti105-publication-simplifiee.json",
    "size" : 1258,
    "processes" : [{
      "activity" : "loadResources",
      "start" : 116,
      "length" : 1
    },
    {
      "activity" : "generateNarratives",
      "start" : 123,
      "length" : 10
    },
    {
      "activity" : "validate",
      "start" : 142,
      "length" : 35
    },
    {
      "activity" : "translate",
      "start" : 142,
      "length" : 4
    },
    {
      "activity" : "generate1",
      "start" : 144,
      "length" : 13
    },
    {
      "activity" : "generate2",
      "start" : 158,
      "length" : 23
    }]
  },
  {
    "name" : "/fsh-generated/includes/menu.xml",
    "size" : 3665,
    "processes" : [{
      "activity" : "generate1",
      "start" : 144,
      "length" : 1
    },
    {
      "activity" : "generate2",
      "start" : 158,
      "length" : 1
    }]
  },
  {
    "name" : "/fsh-generated/includes/fsh-link-references.md",
    "size" : 2234,
    "processes" : [{
      "activity" : "validate",
      "start" : 142,
      "length" : 1
    },
    {
      "activity" : "generate2",
      "start" : 158,
      "length" : 1
    }]
  },
  {
    "name" : "/input/data/features.yml",
    "size" : 164
  },
  {
    "name" : "/input/pagecontent/securite.md",
    "size" : 900
  },
  {
    "name" : "/input/pagecontent/transaction_td3.3a.md",
    "size" : 4695,
    "processes" : [{
      "activity" : "validate",
      "start" : 142,
      "length" : 1
    }]
  },
  {
    "name" : "/input/pagecontent/transaction_td3.3c.md",
    "size" : 3209,
    "processes" : [{
      "activity" : "generate2",
      "start" : 158,
      "length" : 1
    }]
  },
  {
    "name" : "/input/pagecontent/autres_ressources.md",
    "size" : 155,
    "processes" : [{
      "activity" : "validate",
      "start" : 142,
      "length" : 1
    }]
  },
  {
    "name" : "/input/pagecontent/annexe.md",
    "size" : 119
  },
  {
    "name" : "/input/pagecontent/tests.md",
    "size" : 1184,
    "processes" : [{
      "activity" : "validate",
      "start" : 142,
      "length" : 1
    }]
  },
  {
    "name" : "/input/pagecontent/StructureDefinition-SourcePatientInfo-intro.md",
    "size" : 232
  },
  {
    "name" : "/input/pagecontent/transaction_td3.1b.md",
    "size" : 3446,
    "processes" : [{
      "activity" : "validate",
      "start" : 142,
      "length" : 1
    },
    {
      "activity" : "generate2",
      "start" : 158,
      "length" : 1
    }]
  },
  {
    "name" : "/input/pagecontent/annexe_dates_xds_fhir.md",
    "size" : 3637
  },
  {
    "name" : "/input/pagecontent/StructureDefinition-Author-intro.md",
    "size" : 165
  },
  {
    "name" : "/input/pagecontent/transaction_td3.1a.md",
    "size" : 6458,
    "processes" : [{
      "activity" : "validate",
      "start" : 142,
      "length" : 1
    },
    {
      "activity" : "generate2",
      "start" : 158,
      "length" : 1
    }]
  },
  {
    "name" : "/input/pagecontent/transaction_td2.1.md",
    "size" : 4423
  },
  {
    "name" : "/input/pagecontent/StructureDefinition-PatientId-intro.md",
    "size" : 330,
    "processes" : [{
      "activity" : "validate",
      "start" : 142,
      "length" : 1
    }]
  },
  {
    "name" : "/input/pagecontent/transaction_td3.3d.md",
    "size" : 4108,
    "processes" : [{
      "activity" : "generate2",
      "start" : 158,
      "length" : 1
    }]
  },
  {
    "name" : "/input/pagecontent/transaction_td3.3b.md",
    "size" : 4904,
    "processes" : [{
      "activity" : "validate",
      "start" : 142,
      "length" : 1
    }]
  },
  {
    "name" : "/input/pagecontent/StructureDefinition-LegalAuthentificator.md",
    "size" : 442
  },
  {
    "name" : "/input/pagecontent/exemples_usage_dmp.md",
    "size" : 16435,
    "processes" : [{
      "activity" : "validate",
      "start" : 142,
      "length" : 1
    },
    {
      "activity" : "generate2",
      "start" : 158,
      "length" : 1
    }]
  },
  {
    "name" : "/input/pagecontent/transaction_td02.md",
    "size" : 7017,
    "processes" : [{
      "activity" : "generate2",
      "start" : 158,
      "length" : 1
    }]
  },
  {
    "name" : "/input/pagecontent/StructureDefinition-AuthorPerson-intro.md",
    "size" : 489,
    "processes" : [{
      "activity" : "validate",
      "start" : 142,
      "length" : 1
    }]
  },
  {
    "name" : "/input/pagecontent/annexe_identifiants_xds_fhir.md",
    "size" : 4160,
    "processes" : [{
      "activity" : "scan",
      "start" : 118,
      "length" : 1
    },
    {
      "activity" : "generate2",
      "start" : 158,
      "length" : 1
    }]
  },
  {
    "name" : "/input/pagecontent/downloads.md",
    "size" : 1727,
    "processes" : [{
      "activity" : "validate",
      "start" : 142,
      "length" : 1
    }]
  },
  {
    "name" : "/input/pagecontent/change-log.md",
    "size" : 1214,
    "processes" : [{
      "activity" : "generate2",
      "start" : 158,
      "length" : 1
    }]
  },
  {
    "name" : "/input/pagecontent/StructureDefinition-AuthorInstitution-intro.md",
    "size" : 159,
    "processes" : [{
      "activity" : "validate",
      "start" : 142,
      "length" : 1
    }]
  },
  {
    "name" : "/input/pagecontent/translationinfo.md",
    "size" : 157,
    "processes" : [{
      "activity" : "generate2",
      "start" : 158,
      "length" : 1
    }]
  },
  {
    "name" : "/input/pagecontent/index.md",
    "size" : 7148,
    "processes" : [{
      "activity" : "scan",
      "start" : 118,
      "length" : 1
    },
    {
      "activity" : "validate",
      "start" : 142,
      "length" : 1
    },
    {
      "activity" : "generate2",
      "start" : 158,
      "length" : 1
    }]
  },
  {
    "name" : "/input/pagecontent/transaction_td3.2.md",
    "size" : 4118
  },
  {
    "name" : "/input/pagecontent/StructureDefinition-SourcePatientId-intro.md",
    "size" : 54
  },
  {
    "name" : "/input/pagecontent/specifications_fonctionnelles.md",
    "size" : 0,
    "processes" : [{
      "activity" : "validate",
      "start" : 142,
      "length" : 1
    },
    {
      "activity" : "generate2",
      "start" : 158,
      "length" : 1
    }]
  },
  {
    "name" : "/input/pagecontent/transaction_td2.md",
    "size" : 4887
  },
  {
    "name" : "/input/pagecontent/specifications_techniques.md",
    "size" : 0,
    "processes" : [{
      "activity" : "validate",
      "start" : 142,
      "length" : 1
    },
    {
      "activity" : "generate2",
      "start" : 158,
      "length" : 1
    }]
  },
  {
    "name" : "/template/config",
    "size" : 0
  },
  {
    "name" : "/template/config/_config.yml",
    "size" : 140,
    "processes" : [{
      "activity" : "validate",
      "start" : 142,
      "length" : 1
    }]
  },
  {
    "name" : "/input/images",
    "size" : 0
  },
  {
    "name" : "/input/images/ci-sis-logo.png",
    "size" : 61365,
    "processes" : [{
      "activity" : "validate",
      "start" : 142,
      "length" : 1
    },
    {
      "activity" : "generate2",
      "start" : 158,
      "length" : 1
    }]
  },
  {
    "name" : "/input/images/anImage.png",
    "size" : 36288
  },
  {
    "name" : "/temp/pages/_includes/artifacts.xml",
    "size" : 28392,
    "processes" : [{
      "activity" : "generate2",
      "start" : 158,
      "length" : 2
    }]
  }]
}
