{
  "date" : "Mon, 05 May, 2025 08:02:26 +0000",
  "doco" : "For each file: start is seconds after start activity occurred. Length = milliseconds activity took",
  "files" : [
    {
      "name" : "/fsh-generated/resources/ImplementationGuide-ans.fhir.fr.pdsm4dmp.json",
      "size" : 17842,
      "processes" : [
        {
          "activity" : "load",
          "start" : 93,
          "length" : 62
        },
        {
          "activity" : "load-configure",
          "start" : 95,
          "length" : 1
        },
        {
          "activity" : "checkR4R4B",
          "start" : 95,
          "length" : 5
        },
        {
          "activity" : "generateNarratives",
          "start" : 95,
          "length" : 491
        },
        {
          "activity" : "validate",
          "start" : 116,
          "length" : 38538
        },
        {
          "activity" : "scanForUsageStats",
          "start" : 155,
          "length" : 1
        },
        {
          "activity" : "generate1",
          "start" : 155,
          "length" : 204
        },
        {
          "activity" : "generate2",
          "start" : 164,
          "length" : 242
        },
        {
          "activity" : "generateValidationPack",
          "start" : 190,
          "length" : 5
        }
      ]
    },
    {
      "name" : "fsh-generated/resources/Binary-AuthorDispositif.json",
      "size" : 1341,
      "processes" : [
        {
          "activity" : "loadResources",
          "start" : 90,
          "length" : 59
        },
        {
          "activity" : "generate1",
          "start" : 155,
          "length" : 119
        },
        {
          "activity" : "generate2",
          "start" : 164,
          "length" : 128
        },
        {
          "activity" : "generateExampleZip",
          "start" : 190,
          "length" : 1
        }
      ]
    },
    {
      "name" : "fsh-generated/resources/Binary-AuthorPSCabinetRPPS.json",
      "size" : 1344,
      "processes" : [
        {
          "activity" : "loadResources",
          "start" : 90,
          "length" : 60
        },
        {
          "activity" : "load",
          "start" : 93,
          "length" : 1
        },
        {
          "activity" : "generate1",
          "start" : 155,
          "length" : 115
        },
        {
          "activity" : "generate2",
          "start" : 164,
          "length" : 130
        }
      ]
    },
    {
      "name" : "fsh-generated/resources/Binary-AuthorPatient.json",
      "size" : 1338,
      "processes" : [
        {
          "activity" : "loadResources",
          "start" : 90,
          "length" : 69
        },
        {
          "activity" : "checkR4R4B",
          "start" : 95,
          "length" : 1
        },
        {
          "activity" : "generate1",
          "start" : 155,
          "length" : 132
        },
        {
          "activity" : "generate2",
          "start" : 165,
          "length" : 115
        }
      ]
    },
    {
      "name" : "fsh-generated/resources/Binary-AuthorStructure.json",
      "size" : 1340,
      "processes" : [
        {
          "activity" : "loadResources",
          "start" : 90,
          "length" : 69
        },
        {
          "activity" : "generate1",
          "start" : 155,
          "length" : 118
        },
        {
          "activity" : "generate2",
          "start" : 165,
          "length" : 121
        }
      ]
    },
    {
      "name" : "fsh-generated/resources/ConceptMap-documentReferenceToPDSM.json",
      "size" : 7347,
      "processes" : [
        {
          "activity" : "loadResources",
          "start" : 90,
          "length" : 72
        },
        {
          "activity" : "load",
          "start" : 92,
          "length" : 61
        },
        {
          "activity" : "load",
          "start" : 93,
          "length" : 54
        },
        {
          "activity" : "generateNarratives",
          "start" : 96,
          "length" : 1181
        },
        {
          "activity" : "validate",
          "start" : 99,
          "length" : 1931
        },
        {
          "activity" : "generate1",
          "start" : 156,
          "length" : 141
        },
        {
          "activity" : "generate2",
          "start" : 165,
          "length" : 529
        },
        {
          "activity" : "generateValidationPack",
          "start" : 191,
          "length" : 2
        }
      ]
    },
    {
      "name" : "fsh-generated/resources/ConceptMap-submissionSetToPDSM.json",
      "size" : 3199,
      "processes" : [
        {
          "activity" : "loadResources",
          "start" : 90,
          "length" : 62
        },
        {
          "activity" : "load",
          "start" : 92,
          "length" : 57
        },
        {
          "activity" : "load",
          "start" : 93,
          "length" : 57
        },
        {
          "activity" : "load-configure",
          "start" : 95,
          "length" : 1
        },
        {
          "activity" : "checkR4R4B",
          "start" : 95,
          "length" : 1
        },
        {
          "activity" : "generateNarratives",
          "start" : 97,
          "length" : 1145
        },
        {
          "activity" : "validate",
          "start" : 101,
          "length" : 152
        },
        {
          "activity" : "generate1",
          "start" : 156,
          "length" : 131
        },
        {
          "activity" : "generate2",
          "start" : 165,
          "length" : 126
        }
      ]
    },
    {
      "name" : "fsh-generated/resources/StructureDefinition-ActorPS.json",
      "size" : 1920,
      "processes" : [
        {
          "activity" : "loadResources",
          "start" : 90,
          "length" : 69
        },
        {
          "activity" : "load",
          "start" : 92,
          "length" : 53
        },
        {
          "activity" : "generateSnapshots",
          "start" : 93,
          "length" : 151
        },
        {
          "activity" : "generateNarratives",
          "start" : 98,
          "length" : 82
        },
        {
          "activity" : "validate",
          "start" : 101,
          "length" : 686
        },
        {
          "activity" : "checkConformanceResources",
          "start" : 155,
          "length" : 1
        },
        {
          "activity" : "scanForUsageStats",
          "start" : 155,
          "length" : 1
        },
        {
          "activity" : "generate1",
          "start" : 156,
          "length" : 154
        },
        {
          "activity" : "generate2",
          "start" : 165,
          "length" : 371
        },
        {
          "activity" : "generate2",
          "start" : 167,
          "length" : 427
        },
        {
          "activity" : "generateValidationPack",
          "start" : 191,
          "length" : 2
        },
        {
          "activity" : "scanExamplesForR5",
          "start" : 201,
          "length" : 1
        }
      ]
    },
    {
      "name" : "fsh-generated/resources/StructureDefinition-ActorPatient.json",
      "size" : 1954,
      "processes" : [
        {
          "activity" : "loadResources",
          "start" : 91,
          "length" : 55
        },
        {
          "activity" : "load",
          "start" : 92,
          "length" : 51
        },
        {
          "activity" : "generateSnapshots",
          "start" : 93,
          "length" : 50
        },
        {
          "activity" : "generateNarratives",
          "start" : 98,
          "length" : 64
        },
        {
          "activity" : "validate",
          "start" : 102,
          "length" : 567
        },
        {
          "activity" : "generate1",
          "start" : 156,
          "length" : 149
        },
        {
          "activity" : "generate2",
          "start" : 166,
          "length" : 154
        },
        {
          "activity" : "generate2",
          "start" : 168,
          "length" : 105
        },
        {
          "activity" : "generateValidationPack",
          "start" : 191,
          "length" : 1
        }
      ]
    },
    {
      "name" : "fsh-generated/resources/StructureDefinition-ActorSNR.json",
      "size" : 2007,
      "processes" : [
        {
          "activity" : "loadResources",
          "start" : 91,
          "length" : 69
        },
        {
          "activity" : "load",
          "start" : 92,
          "length" : 70
        },
        {
          "activity" : "generateSnapshots",
          "start" : 93,
          "length" : 40
        },
        {
          "activity" : "generateNarratives",
          "start" : 98,
          "length" : 62
        },
        {
          "activity" : "validate",
          "start" : 103,
          "length" : 582
        },
        {
          "activity" : "generate1",
          "start" : 156,
          "length" : 152
        },
        {
          "activity" : "generate2",
          "start" : 166,
          "length" : 123
        },
        {
          "activity" : "generate2",
          "start" : 168,
          "length" : 98
        },
        {
          "activity" : "generateValidationPack",
          "start" : 191,
          "length" : 1
        }
      ]
    },
    {
      "name" : "fsh-generated/resources/StructureDefinition-ActorSystem.json",
      "size" : 2054,
      "processes" : [
        {
          "activity" : "loadResources",
          "start" : 91,
          "length" : 69
        },
        {
          "activity" : "load",
          "start" : 92,
          "length" : 70
        },
        {
          "activity" : "generateSnapshots",
          "start" : 94,
          "length" : 43
        },
        {
          "activity" : "generateNarratives",
          "start" : 98,
          "length" : 62
        },
        {
          "activity" : "validate",
          "start" : 103,
          "length" : 514
        },
        {
          "activity" : "generate1",
          "start" : 156,
          "length" : 148
        },
        {
          "activity" : "generate2",
          "start" : 166,
          "length" : 108
        },
        {
          "activity" : "generate2",
          "start" : 168,
          "length" : 80
        },
        {
          "activity" : "generateValidationPack",
          "start" : 191,
          "length" : 2
        }
      ]
    },
    {
      "name" : "fsh-generated/resources/StructureDefinition-ActorXDS.json",
      "size" : 6198,
      "processes" : [
        {
          "activity" : "loadResources",
          "start" : 91,
          "length" : 70
        },
        {
          "activity" : "load",
          "start" : 92,
          "length" : 53
        },
        {
          "activity" : "generateSnapshots",
          "start" : 94,
          "length" : 1
        },
        {
          "activity" : "generateNarratives",
          "start" : 98,
          "length" : 58
        },
        {
          "activity" : "validate",
          "start" : 104,
          "length" : 813
        },
        {
          "activity" : "scanForUsageStats",
          "start" : 155,
          "length" : 1
        },
        {
          "activity" : "generate1",
          "start" : 156,
          "length" : 155
        },
        {
          "activity" : "generate2",
          "start" : 166,
          "length" : 104
        },
        {
          "activity" : "generate2",
          "start" : 168,
          "length" : 115
        },
        {
          "activity" : "generateValidationPack",
          "start" : 191,
          "length" : 1
        }
      ]
    },
    {
      "name" : "fsh-generated/resources/StructureDefinition-Author.json",
      "size" : 4559,
      "processes" : [
        {
          "activity" : "loadResources",
          "start" : 91,
          "length" : 69
        },
        {
          "activity" : "load",
          "start" : 92,
          "length" : 51
        },
        {
          "activity" : "generateSnapshots",
          "start" : 94,
          "length" : 37
        },
        {
          "activity" : "load-configure",
          "start" : 95,
          "length" : 1
        },
        {
          "activity" : "loadInfo",
          "start" : 95,
          "length" : 1
        },
        {
          "activity" : "generateNarratives",
          "start" : 98,
          "length" : 86
        },
        {
          "activity" : "validate",
          "start" : 105,
          "length" : 549
        },
        {
          "activity" : "generate1",
          "start" : 157,
          "length" : 142
        },
        {
          "activity" : "generate2",
          "start" : 166,
          "length" : 113
        },
        {
          "activity" : "generate2",
          "start" : 168,
          "length" : 65
        },
        {
          "activity" : "generateValidationPack",
          "start" : 191,
          "length" : 1
        }
      ]
    },
    {
      "name" : "fsh-generated/resources/StructureDefinition-AuthorDocumentEntry.json",
      "size" : 4245,
      "processes" : [
        {
          "activity" : "loadResources",
          "start" : 91,
          "length" : 63
        },
        {
          "activity" : "load",
          "start" : 92,
          "length" : 71
        },
        {
          "activity" : "generateSnapshots",
          "start" : 94,
          "length" : 63
        },
        {
          "activity" : "generateNarratives",
          "start" : 98,
          "length" : 60
        },
        {
          "activity" : "validate",
          "start" : 105,
          "length" : 363
        },
        {
          "activity" : "generate1",
          "start" : 157,
          "length" : 149
        },
        {
          "activity" : "generate2",
          "start" : 166,
          "length" : 75
        },
        {
          "activity" : "generate2",
          "start" : 168,
          "length" : 58
        },
        {
          "activity" : "generateValidationPack",
          "start" : 191,
          "length" : 1
        }
      ]
    },
    {
      "name" : "fsh-generated/resources/StructureDefinition-AuthorInstitution.json",
      "size" : 6022,
      "processes" : [
        {
          "activity" : "loadResources",
          "start" : 91,
          "length" : 69
        },
        {
          "activity" : "load",
          "start" : 92,
          "length" : 52
        },
        {
          "activity" : "generateSnapshots",
          "start" : 94,
          "length" : 57
        },
        {
          "activity" : "generateNarratives",
          "start" : 98,
          "length" : 57
        },
        {
          "activity" : "validate",
          "start" : 105,
          "length" : 716
        },
        {
          "activity" : "generate1",
          "start" : 157,
          "length" : 152
        },
        {
          "activity" : "generate2",
          "start" : 166,
          "length" : 95
        },
        {
          "activity" : "generate2",
          "start" : 168,
          "length" : 72
        },
        {
          "activity" : "generateValidationPack",
          "start" : 191,
          "length" : 2
        },
        {
          "activity" : "scanProfilesForR5",
          "start" : 201,
          "length" : 1
        }
      ]
    },
    {
      "name" : "fsh-generated/resources/StructureDefinition-AuthorSubmissionSet.json",
      "size" : 2395,
      "processes" : [
        {
          "activity" : "loadResources",
          "start" : 91,
          "length" : 70
        },
        {
          "activity" : "load",
          "start" : 92,
          "length" : 51
        },
        {
          "activity" : "generateSnapshots",
          "start" : 94,
          "length" : 67
        },
        {
          "activity" : "generateNarratives",
          "start" : 99,
          "length" : 59
        },
        {
          "activity" : "validate",
          "start" : 106,
          "length" : 321
        },
        {
          "activity" : "generate1",
          "start" : 157,
          "length" : 149
        },
        {
          "activity" : "generate2",
          "start" : 167,
          "length" : 77
        },
        {
          "activity" : "generate2",
          "start" : 168,
          "length" : 54
        },
        {
          "activity" : "generateValidationPack",
          "start" : 191,
          "length" : 1
        }
      ]
    },
    {
      "name" : "fsh-generated/resources/StructureDefinition-DocumentEntry.json",
      "size" : 19253,
      "processes" : [
        {
          "activity" : "loadResources",
          "start" : 91,
          "length" : 70
        },
        {
          "activity" : "load",
          "start" : 92,
          "length" : 55
        },
        {
          "activity" : "generateSnapshots",
          "start" : 94,
          "length" : 81
        },
        {
          "activity" : "generateNarratives",
          "start" : 99,
          "length" : 122
        },
        {
          "activity" : "validate",
          "start" : 106,
          "length" : 3074
        },
        {
          "activity" : "scanForUsageStats",
          "start" : 155,
          "length" : 1
        },
        {
          "activity" : "generate1",
          "start" : 157,
          "length" : 246
        },
        {
          "activity" : "generate2",
          "start" : 167,
          "length" : 188
        },
        {
          "activity" : "generate2",
          "start" : 169,
          "length" : 185
        },
        {
          "activity" : "generateValidationPack",
          "start" : 191,
          "length" : 4
        }
      ]
    },
    {
      "name" : "fsh-generated/resources/StructureDefinition-EventCode.json",
      "size" : 1766,
      "processes" : [
        {
          "activity" : "loadResources",
          "start" : 91,
          "length" : 59
        },
        {
          "activity" : "load",
          "start" : 93,
          "length" : 51
        },
        {
          "activity" : "generateSnapshots",
          "start" : 94,
          "length" : 44
        },
        {
          "activity" : "generateNarratives",
          "start" : 99,
          "length" : 56
        },
        {
          "activity" : "validate",
          "start" : 110,
          "length" : 243
        },
        {
          "activity" : "generate1",
          "start" : 157,
          "length" : 131
        },
        {
          "activity" : "generate2",
          "start" : 167,
          "length" : 55
        },
        {
          "activity" : "generate2",
          "start" : 169,
          "length" : 35
        },
        {
          "activity" : "generateValidationPack",
          "start" : 191,
          "length" : 1
        }
      ]
    },
    {
      "name" : "fsh-generated/resources/StructureDefinition-IdentifiantSysteme.json",
      "size" : 1059,
      "processes" : [
        {
          "activity" : "loadResources",
          "start" : 91,
          "length" : 68
        },
        {
          "activity" : "load",
          "start" : 93,
          "length" : 55
        },
        {
          "activity" : "generateSnapshots",
          "start" : 94,
          "length" : 43
        },
        {
          "activity" : "load-configure",
          "start" : 95,
          "length" : 1
        },
        {
          "activity" : "scan",
          "start" : 95,
          "length" : 1
        },
        {
          "activity" : "generateNarratives",
          "start" : 99,
          "length" : 56
        },
        {
          "activity" : "validate",
          "start" : 110,
          "length" : 748
        },
        {
          "activity" : "generate1",
          "start" : 158,
          "length" : 132
        },
        {
          "activity" : "generate2",
          "start" : 167,
          "length" : 61
        },
        {
          "activity" : "generate2",
          "start" : 169,
          "length" : 51
        },
        {
          "activity" : "generateValidationPack",
          "start" : 191,
          "length" : 1
        }
      ]
    },
    {
      "name" : "fsh-generated/resources/StructureDefinition-MatriculeINS.json",
      "size" : 766,
      "processes" : [
        {
          "activity" : "loadResources",
          "start" : 91,
          "length" : 72
        },
        {
          "activity" : "load",
          "start" : 93,
          "length" : 56
        },
        {
          "activity" : "generateSnapshots",
          "start" : 94,
          "length" : 81
        },
        {
          "activity" : "generateNarratives",
          "start" : 99,
          "length" : 55
        },
        {
          "activity" : "validate",
          "start" : 111,
          "length" : 715
        },
        {
          "activity" : "generate1",
          "start" : 158,
          "length" : 132
        },
        {
          "activity" : "generate2",
          "start" : 167,
          "length" : 58
        },
        {
          "activity" : "generate2",
          "start" : 169,
          "length" : 45
        }
      ]
    },
    {
      "name" : "fsh-generated/resources/StructureDefinition-PSIdNat.json",
      "size" : 1009,
      "processes" : [
        {
          "activity" : "loadResources",
          "start" : 91,
          "length" : 69
        },
        {
          "activity" : "load",
          "start" : 93,
          "length" : 56
        },
        {
          "activity" : "generateSnapshots",
          "start" : 94,
          "length" : 42
        },
        {
          "activity" : "generateNarratives",
          "start" : 99,
          "length" : 55
        },
        {
          "activity" : "validate",
          "start" : 111,
          "length" : 716
        },
        {
          "activity" : "generate1",
          "start" : 158,
          "length" : 134
        },
        {
          "activity" : "generate2",
          "start" : 167,
          "length" : 70
        },
        {
          "activity" : "generate2",
          "start" : 169,
          "length" : 41
        },
        {
          "activity" : "generateValidationPack",
          "start" : 191,
          "length" : 1
        }
      ]
    },
    {
      "name" : "fsh-generated/resources/StructureDefinition-PatientId.json",
      "size" : 2201,
      "processes" : [
        {
          "activity" : "loadResources",
          "start" : 91,
          "length" : 68
        },
        {
          "activity" : "load",
          "start" : 93,
          "length" : 56
        },
        {
          "activity" : "generateSnapshots",
          "start" : 94,
          "length" : 48
        },
        {
          "activity" : "generateNarratives",
          "start" : 99,
          "length" : 54
        },
        {
          "activity" : "validate",
          "start" : 112,
          "length" : 382
        },
        {
          "activity" : "generate1",
          "start" : 158,
          "length" : 137
        },
        {
          "activity" : "generate2",
          "start" : 167,
          "length" : 69
        },
        {
          "activity" : "generate2",
          "start" : 169,
          "length" : 37
        },
        {
          "activity" : "generateValidationPack",
          "start" : 191,
          "length" : 1
        }
      ]
    },
    {
      "name" : "fsh-generated/resources/StructureDefinition-SNR.json",
      "size" : 624,
      "processes" : [
        {
          "activity" : "loadResources",
          "start" : 91,
          "length" : 69
        },
        {
          "activity" : "load",
          "start" : 93,
          "length" : 57
        },
        {
          "activity" : "generateSnapshots",
          "start" : 94,
          "length" : 62
        },
        {
          "activity" : "generateNarratives",
          "start" : 99,
          "length" : 54
        },
        {
          "activity" : "validate",
          "start" : 112,
          "length" : 710
        },
        {
          "activity" : "generate1",
          "start" : 158,
          "length" : 132
        },
        {
          "activity" : "generate2",
          "start" : 167,
          "length" : 57
        },
        {
          "activity" : "generate2",
          "start" : 169,
          "length" : 49
        },
        {
          "activity" : "generateValidationPack",
          "start" : 191,
          "length" : 1
        }
      ]
    },
    {
      "name" : "fsh-generated/resources/StructureDefinition-SourcePatientId.json",
      "size" : 2663,
      "processes" : [
        {
          "activity" : "loadResources",
          "start" : 92,
          "length" : 69
        },
        {
          "activity" : "load",
          "start" : 93,
          "length" : 57
        },
        {
          "activity" : "generateSnapshots",
          "start" : 94,
          "length" : 53
        },
        {
          "activity" : "generateNarratives",
          "start" : 99,
          "length" : 55
        },
        {
          "activity" : "validate",
          "start" : 113,
          "length" : 391
        },
        {
          "activity" : "generate1",
          "start" : 158,
          "length" : 136
        },
        {
          "activity" : "generate2",
          "start" : 167,
          "length" : 64
        },
        {
          "activity" : "generate2",
          "start" : 169,
          "length" : 50
        },
        {
          "activity" : "generateValidationPack",
          "start" : 191,
          "length" : 1
        }
      ]
    },
    {
      "name" : "fsh-generated/resources/StructureDefinition-SourcePatientInfo.json",
      "size" : 4957,
      "processes" : [
        {
          "activity" : "loadResources",
          "start" : 92,
          "length" : 68
        },
        {
          "activity" : "load",
          "start" : 93,
          "length" : 58
        },
        {
          "activity" : "generateSnapshots",
          "start" : 94,
          "length" : 55
        },
        {
          "activity" : "generateNarratives",
          "start" : 99,
          "length" : 67
        },
        {
          "activity" : "validate",
          "start" : 113,
          "length" : 956
        },
        {
          "activity" : "generate1",
          "start" : 158,
          "length" : 156
        },
        {
          "activity" : "generate2",
          "start" : 167,
          "length" : 78
        },
        {
          "activity" : "generate2",
          "start" : 169,
          "length" : 70
        },
        {
          "activity" : "generateValidationPack",
          "start" : 191,
          "length" : 3
        }
      ]
    },
    {
      "name" : "fsh-generated/resources/StructureDefinition-StructIdNat.json",
      "size" : 887,
      "processes" : [
        {
          "activity" : "loadResources",
          "start" : 92,
          "length" : 69
        },
        {
          "activity" : "load",
          "start" : 93,
          "length" : 56
        },
        {
          "activity" : "generateSnapshots",
          "start" : 94,
          "length" : 53
        },
        {
          "activity" : "generateNarratives",
          "start" : 99,
          "length" : 74
        },
        {
          "activity" : "validate",
          "start" : 114,
          "length" : 704
        },
        {
          "activity" : "generate1",
          "start" : 159,
          "length" : 134
        },
        {
          "activity" : "generate2",
          "start" : 167,
          "length" : 56
        },
        {
          "activity" : "generate2",
          "start" : 169,
          "length" : 42
        },
        {
          "activity" : "generateValidationPack",
          "start" : 191,
          "length" : 1
        }
      ]
    },
    {
      "name" : "fsh-generated/resources/StructureDefinition-SubmissionSet.json",
      "size" : 8028,
      "processes" : [
        {
          "activity" : "loadResources",
          "start" : 92,
          "length" : 69
        },
        {
          "activity" : "load",
          "start" : 93,
          "length" : 62
        },
        {
          "activity" : "generateSnapshots",
          "start" : 94,
          "length" : 59
        },
        {
          "activity" : "load-configure",
          "start" : 95,
          "length" : 1
        },
        {
          "activity" : "loadDepInfo",
          "start" : 95,
          "length" : 1
        },
        {
          "activity" : "generateNarratives",
          "start" : 99,
          "length" : 60
        },
        {
          "activity" : "validate",
          "start" : 115,
          "length" : 1042
        },
        {
          "activity" : "generate1",
          "start" : 159,
          "length" : 176
        },
        {
          "activity" : "generate2",
          "start" : 167,
          "length" : 102
        },
        {
          "activity" : "generate2",
          "start" : 169,
          "length" : 72
        },
        {
          "activity" : "generateValidationPack",
          "start" : 191,
          "length" : 2
        },
        {
          "activity" : "scanExamplesForR5",
          "start" : 201,
          "length" : 2
        }
      ]
    }
  ]
}
