{
  "date" : "Tue, 06 May, 2025 07:37:31 +0000",
  "doco" : "For each file: start is seconds after start activity occurred. Length = milliseconds activity took",
  "files" : [
    {
      "name" : "/fsh-generated/resources/ImplementationGuide-ans.fhir.fr.pdsm4dmp.json",
      "size" : 4411,
      "processes" : [
        {
          "activity" : "load",
          "start" : 82,
          "length" : 63
        },
        {
          "activity" : "checkR4R4B",
          "start" : 83,
          "length" : 4
        },
        {
          "activity" : "generateNarratives",
          "start" : 83,
          "length" : 240
        },
        {
          "activity" : "validate",
          "start" : 89,
          "length" : 33855
        },
        {
          "activity" : "scanForUsageStats",
          "start" : 123,
          "length" : 1
        },
        {
          "activity" : "generate1",
          "start" : 123,
          "length" : 220
        },
        {
          "activity" : "generate2",
          "start" : 126,
          "length" : 162
        },
        {
          "activity" : "generateValidationPack",
          "start" : 145,
          "length" : 3
        },
        {
          "activity" : "scanExamplesForR5",
          "start" : 152,
          "length" : 2
        }
      ]
    },
    {
      "name" : "fsh-generated/resources/StructureDefinition-ActorChild.json",
      "size" : 1422,
      "processes" : [
        {
          "activity" : "loadResources",
          "start" : 82,
          "length" : 41
        },
        {
          "activity" : "load",
          "start" : 82,
          "length" : 43
        },
        {
          "activity" : "generateSnapshots",
          "start" : 82,
          "length" : 173
        },
        {
          "activity" : "load-configure",
          "start" : 83,
          "length" : 1
        },
        {
          "activity" : "generateNarratives",
          "start" : 83,
          "length" : 65
        },
        {
          "activity" : "validate",
          "start" : 84,
          "length" : 2298
        },
        {
          "activity" : "generate1",
          "start" : 123,
          "length" : 130
        },
        {
          "activity" : "generate2",
          "start" : 126,
          "length" : 354
        },
        {
          "activity" : "generate2",
          "start" : 127,
          "length" : 760
        },
        {
          "activity" : "generateValidationPack",
          "start" : 145,
          "length" : 1
        }
      ]
    },
    {
      "name" : "fsh-generated/resources/StructureDefinition-ActorChild2.json",
      "size" : 1781,
      "processes" : [
        {
          "activity" : "loadResources",
          "start" : 82,
          "length" : 36
        },
        {
          "activity" : "load",
          "start" : 82,
          "length" : 40
        },
        {
          "activity" : "generateSnapshots",
          "start" : 82,
          "length" : 49
        },
        {
          "activity" : "generateNarratives",
          "start" : 83,
          "length" : 47
        },
        {
          "activity" : "validate",
          "start" : 86,
          "length" : 368
        },
        {
          "activity" : "generate1",
          "start" : 123,
          "length" : 135
        },
        {
          "activity" : "generate2",
          "start" : 127,
          "length" : 160
        },
        {
          "activity" : "generate2",
          "start" : 128,
          "length" : 102
        },
        {
          "activity" : "generateValidationPack",
          "start" : 145,
          "length" : 1
        }
      ]
    },
    {
      "name" : "fsh-generated/resources/StructureDefinition-ActorParent.json",
      "size" : 2701,
      "processes" : [
        {
          "activity" : "loadResources",
          "start" : 82,
          "length" : 36
        },
        {
          "activity" : "load",
          "start" : 82,
          "length" : 43
        },
        {
          "activity" : "generateNarratives",
          "start" : 84,
          "length" : 47
        },
        {
          "activity" : "validate",
          "start" : 86,
          "length" : 378
        },
        {
          "activity" : "generate1",
          "start" : 124,
          "length" : 132
        },
        {
          "activity" : "generate2",
          "start" : 127,
          "length" : 123
        },
        {
          "activity" : "generate2",
          "start" : 128,
          "length" : 71
        },
        {
          "activity" : "generateValidationPack",
          "start" : 145,
          "length" : 1
        }
      ]
    },
    {
      "name" : "fsh-generated/resources/StructureDefinition-Choice1.json",
      "size" : 742,
      "processes" : [
        {
          "activity" : "loadResources",
          "start" : 82,
          "length" : 36
        },
        {
          "activity" : "load",
          "start" : 82,
          "length" : 39
        },
        {
          "activity" : "generateSnapshots",
          "start" : 83,
          "length" : 66
        },
        {
          "activity" : "generateNarratives",
          "start" : 84,
          "length" : 49
        },
        {
          "activity" : "validate",
          "start" : 87,
          "length" : 800
        },
        {
          "activity" : "generate1",
          "start" : 124,
          "length" : 132
        },
        {
          "activity" : "generate2",
          "start" : 127,
          "length" : 112
        },
        {
          "activity" : "generate2",
          "start" : 128,
          "length" : 78
        },
        {
          "activity" : "generateValidationPack",
          "start" : 145,
          "length" : 1
        }
      ]
    },
    {
      "name" : "fsh-generated/resources/StructureDefinition-Choice2.json",
      "size" : 1406,
      "processes" : [
        {
          "activity" : "loadResources",
          "start" : 82,
          "length" : 41
        },
        {
          "activity" : "load",
          "start" : 82,
          "length" : 39
        },
        {
          "activity" : "generateSnapshots",
          "start" : 83,
          "length" : 51
        },
        {
          "activity" : "generateNarratives",
          "start" : 84,
          "length" : 44
        },
        {
          "activity" : "validate",
          "start" : 88,
          "length" : 724
        },
        {
          "activity" : "generate1",
          "start" : 124,
          "length" : 134
        },
        {
          "activity" : "generate2",
          "start" : 127,
          "length" : 99
        },
        {
          "activity" : "generate2",
          "start" : 128,
          "length" : 64
        },
        {
          "activity" : "generateValidationPack",
          "start" : 145,
          "length" : 1
        }
      ]
    },
    {
      "name" : "fsh-generated/resources/StructureDefinition-Choice3.json",
      "size" : 636,
      "processes" : [
        {
          "activity" : "loadResources",
          "start" : 82,
          "length" : 42
        },
        {
          "activity" : "load",
          "start" : 82,
          "length" : 44
        },
        {
          "activity" : "generateSnapshots",
          "start" : 83,
          "length" : 43
        },
        {
          "activity" : "generateNarratives",
          "start" : 84,
          "length" : 52
        },
        {
          "activity" : "validate",
          "start" : 88,
          "length" : 699
        },
        {
          "activity" : "generate1",
          "start" : 124,
          "length" : 126
        },
        {
          "activity" : "generate2",
          "start" : 127,
          "length" : 102
        },
        {
          "activity" : "generate2",
          "start" : 128,
          "length" : 55
        },
        {
          "activity" : "generateValidationPack",
          "start" : 145,
          "length" : 1
        }
      ]
    }
  ]
}
